napari_stracking/__init__.py
napari_stracking/_dock_widget.py
napari_stracking/_export_plugin.py
napari_stracking/_pipeline_plugin.py
napari_stracking/_reader_plugin.py
napari_stracking/_scale_plugin.py
napari_stracking/_sdetection_plugins.py
napari_stracking/_sdetection_workers.py
napari_stracking/_sfeatures_plugins.py
napari_stracking/_sfeatures_workers.py
napari_stracking/_slinking_plugins.py
napari_stracking/_slinking_workers.py
napari_stracking/_splugin.py
napari_stracking/_sproperties_plugins.py
napari_stracking/_sproperties_workers.py
napari_stracking/_strackfilter_plugins.py
napari_stracking/_strackfilter_workers.py
napari_stracking/_swidgets.py
napari_stracking/_tests/__init__.py
napari_stracking/_tests/test_dock_widget.py
napari_stracking-0.1.10.dist-info/LICENSE
napari_stracking-0.1.10.dist-info/METADATA
napari_stracking-0.1.10.dist-info/WHEEL
napari_stracking-0.1.10.dist-info/entry_points.txt
napari_stracking-0.1.10.dist-info/top_level.txt
napari_stracking-0.1.10.dist-info/RECORD
