Metadata-Version: 2.1
Name: napari-stracking
Version: 0.1.10
Summary: Linking and tracks analysis
Home-page: https://github.com/sylvainprigent/napari-stracking
Author: Sylvain Prigent
Author-email: sylvain.prigent@inria.fr
License: BSD 3-Clause
Project-URL: Bug Tracker, https://github.com/sylvainprigent/napari-stracking/issues
Project-URL: Documentation, https://github.com/sylvainprigent/napari-stracking#README.md
Project-URL: Source Code, https://github.com/sylvainprigent/napari-stracking
Project-URL: User Support, https://github.com/sylvainprigent/napari-stracking/issues
Classifier: Development Status :: 2 - Pre-Alpha
Classifier: Intended Audience :: Developers
Classifier: Framework :: napari
Classifier: Topic :: Software Development :: Testing
Classifier: Programming Language :: Python
Classifier: Programming Language :: Python :: 3
Classifier: Programming Language :: Python :: 3.8
Classifier: Programming Language :: Python :: 3.9
Classifier: Programming Language :: Python :: 3.10
Classifier: Operating System :: OS Independent
Classifier: License :: OSI Approved :: BSD License
Requires-Python: >=3.8
License-File: LICENSE
Requires-Dist: napari
Requires-Dist: napari-plugin-engine >=0.1.4
Requires-Dist: numpy
Requires-Dist: stracking >=0.1.10
